{
  "codeStatus": "Active",
  "smdgLinerID": "tsk",
  "linerCodeVersion": "V1",
  "linerSMDGCode": "TSK",
  "linerName": "Tokyo Senpaku Kaisha",
  "isActive": true,
  "validFrom": "2003-09-01",
  "validTo": "9999-12-31",
  "parentCompanyCode": "",
  "parentCompanyName": "HLC",
  "carrierType": "",
  "addressLocation": {
    "UnLocode": "",
    "UnCountryCode": "JP",
    "locationName": "",
    "address": {
      "name": "2-19-6 Yanagibashi Taito-Ku, 111-0052 Japan",
      "street": "",
      "streetNumber": "",
      "floor": "",
      "postCode": "",
      "city": "",
      "state": "",
      "country": "Japan"
    }
  },
  "changeLogs": [
    {
      "actionCode": "Added",
      "linerCodeVersion": "V1",
      "lastUpdateDate": "2021-01-01",
      "updateRequestedBy": null,
      "linkedLinerCode": "",
      "reason": "new request",
      "comments": ""
    }
  ],
  "website": "",
  "remarks": ""
}