{
  "isActive": true,
  "codeStatus": "Active",
  "linerCodeVersion": "V1",
  "linerSMDGCode": "TTR",
  "linerName": "Tru-Trans Malaysia",
  "isNVOCC": false,
  "isVOCC": false,
  "parentCompany": "",
  "address": "Pandamaran, 42000 Port Klang, Selangor, Malaysia",
  "addressLocation": {
    "UnLocode": "PKG",
    "UnCountryCode": "MY",
    "address": {
      "street": "",
      "streetNumber": "",
      "floor": "",
      "postCode": "42000",
      "city": "Port Klang",
      "state": "",
      "country": "Malaysia"
    }
  },
  "website": "",
  "remarks": "",
  "validFrom": "2003-09-01",
  "validTo": null,
  "changeLogs": [
    {
      "actionCode": "Added",
      "linerCodeVersion": "V1",
      "lastUpdateDate": "2021-01-01",
      "updateRequestedBy": null,
      "reason": "initial change",
      "changedFields": [],
      "linkedLinerCode": "",
      "comments": "Added by SMDG without a specific request."
    }
  ]
}